[
  { "id": "cm-001", "host": "TBD", "monthYear": "Aug '26", "day": 18, "time": "11:37 AM - 12:13 PM", "location": "MVHS Counseling & Career Center", "details": "TBD", "title": "Club Meeting" },
  { "id": "cm-002", "host": "TBD", "monthYear": "Aug '26", "day": 25, "time": "11:37 AM - 12:13 PM", "location": "MVHS Counseling & Career Center", "details": "TBD", "title": "Club Meeting" },

  { "id": "cm-003", "host": "TBD", "monthYear": "Sep '26", "day": 1, "time": "11:37 AM - 12:13 PM", "location": "MVHS Counseling & Career Center", "details": "TBD", "title": "Club Meeting" },
  { "id": "cm-004", "host": "TBD", "monthYear": "Sep '26", "day": 8, "time": "11:37 AM - 12:13 PM", "location": "MVHS Counseling & Career Center", "details": "TBD", "title": "Club Meeting" },
  { "id": "cm-005", "host": "TBD", "monthYear": "Sep '26", "day": 15, "time": "11:37 AM - 12:13 PM", "location": "MVHS Counseling & Career Center", "details": "TBD", "title": "Club Meeting" },
  { "id": "cm-006", "host": "TBD", "monthYear": "Sep '26", "day": 22, "time": "11:37 AM - 12:13 PM", "location": "MVHS Counseling & Career Center", "details": "TBD", "title": "Club Meeting" },
  { "id": "cm-007", "host": "TBD", "monthYear": "Sep '26", "day": 29, "time": "11:37 AM - 12:13 PM", "location": "MVHS Counseling & Career Center", "details": "TBD", "title": "Club Meeting" },

  { "id": "cm-008", "host": "TBD", "monthYear": "Oct '26", "day": 6, "time": "11:37 AM - 12:13 PM", "location": "MVHS Counseling & Career Center", "details": "TBD", "title": "Club Meeting" },
  { "id": "cm-009", "host": "TBD", "monthYear": "Oct '26", "day": 13, "time": "11:37 AM - 12:13 PM", "location": "MVHS Counseling & Career Center", "details": "TBD", "title": "Club Meeting" },
  { "id": "cm-010", "host": "TBD", "monthYear": "Oct '26", "day": 20, "time": "11:37 AM - 12:13 PM", "location": "MVHS Counseling & Career Center", "details": "TBD", "title": "Club Meeting" },
  { "id": "cm-011", "host": "TBD", "monthYear": "Oct '26", "day": 27, "time": "11:37 AM - 12:13 PM", "location": "MVHS Counseling & Career Center", "details": "TBD", "title": "Club Meeting" },

  { "id": "cm-012", "host": "TBD", "monthYear": "Nov '26", "day": 3, "time": "11:37 AM - 12:13 PM", "location": "MVHS Counseling & Career Center", "details": "TBD", "title": "Club Meeting" },
  { "id": "cm-013", "host": "TBD", "monthYear": "Nov '26", "day": 10, "time": "11:37 AM - 12:13 PM", "location": "MVHS Counseling & Career Center", "details": "TBD", "title": "Club Meeting" },
  { "id": "cm-014", "host": "TBD", "monthYear": "Nov '26", "day": 17, "time": "11:37 AM - 12:13 PM", "location": "MVHS Counseling & Career Center", "details": "TBD", "title": "Club Meeting" },

  { "id": "cm-015", "host": "TBD", "monthYear": "Dec '26", "day": 1, "time": "11:37 AM - 12:13 PM", "location": "MVHS Counseling & Career Center", "details": "TBD", "title": "Club Meeting" },
  { "id": "cm-016", "host": "TBD", "monthYear": "Dec '26", "day": 8, "time": "11:37 AM - 12:13 PM", "location": "MVHS Counseling & Career Center", "details": "TBD", "title": "Club Meeting" },
  { "id": "cm-017", "host": "TBD", "monthYear": "Dec '26", "day": 15, "time": "11:37 AM - 12:13 PM", "location": "MVHS Counseling & Career Center", "details": "TBD", "title": "Club Meeting" },
  { "id": "cm-018", "host": "TBD", "monthYear": "Dec '26", "day": 22, "time": "11:37 AM - 12:13 PM", "location": "MVHS Counseling & Career Center", "details": "TBD", "title": "Club Meeting" },
  { "id": "cm-019", "host": "TBD", "monthYear": "Dec '26", "day": 29, "time": "11:37 AM - 12:13 PM", "location": "MVHS Counseling & Career Center", "details": "TBD", "title": "Club Meeting" },

  { "id": "cm-020", "host": "TBD", "monthYear": "Jan '27", "day": 12, "time": "11:37 AM - 12:13 PM", "location": "MVHS Counseling & Career Center", "details": "TBD", "title": "Club Meeting" },
  { "id": "cm-021", "host": "TBD", "monthYear": "Jan '27", "day": 19, "time": "11:37 AM - 12:13 PM", "location": "MVHS Counseling & Career Center", "details": "TBD", "title": "Club Meeting" },
  { "id": "cm-022", "host": "TBD", "monthYear": "Jan '27", "day": 26, "time": "11:37 AM - 12:13 PM", "location": "MVHS Counseling & Career Center", "details": "TBD", "title": "Club Meeting" },

  { "id": "cm-023", "host": "TBD", "monthYear": "Feb '27", "day": 2, "time": "11:37 AM - 12:13 PM", "location": "MVHS Counseling & Career Center", "details": "TBD", "title": "Club Meeting" },
  { "id": "cm-024", "host": "TBD", "monthYear": "Feb '27", "day": 9, "time": "11:37 AM - 12:13 PM", "location": "MVHS Counseling & Career Center", "details": "TBD", "title": "Club Meeting" },
  { "id": "cm-025", "host": "TBD", "monthYear": "Feb '27", "day": 23, "time": "11:37 AM - 12:13 PM", "location": "MVHS Counseling & Career Center", "details": "TBD", "title": "Club Meeting" },

  { "id": "cm-026", "host": "TBD", "monthYear": "Mar '27", "day": 2, "time": "11:37 AM - 12:13 PM", "location": "MVHS Counseling & Career Center", "details": "TBD", "title": "Club Meeting" },
  { "id": "cm-027", "host": "TBD", "monthYear": "Mar '27", "day": 9, "time": "11:37 AM - 12:13 PM", "location": "MVHS Counseling & Career Center", "details": "TBD", "title": "Club Meeting" },
  { "id": "cm-028", "host": "TBD", "monthYear": "Mar '27", "day": 16, "time": "11:37 AM - 12:13 PM", "location": "MVHS Counseling & Career Center", "details": "TBD", "title": "Club Meeting" },
  { "id": "cm-029", "host": "TBD", "monthYear": "Mar '27", "day": 23, "time": "11:37 AM - 12:13 PM", "location": "MVHS Counseling & Career Center", "details": "TBD", "title": "Club Meeting" },
  { "id": "cm-030", "host": "TBD", "monthYear": "Mar '27", "day": 30, "time": "11:37 AM - 12:13 PM", "location": "MVHS Counseling & Career Center", "details": "TBD", "title": "Club Meeting" },

  { "id": "cm-031", "host": "TBD", "monthYear": "Apr '27", "day": 6, "time": "11:37 AM - 12:13 PM", "location": "MVHS Counseling & Career Center", "details": "TBD", "title": "Club Meeting" },
  { "id": "cm-032", "host": "TBD", "monthYear": "Apr '27", "day": 13, "time": "11:37 AM - 12:13 PM", "location": "MVHS Counseling & Career Center", "details": "TBD", "title": "Club Meeting" },
  { "id": "cm-033", "host": "TBD", "monthYear": "Apr '27", "day": 20, "time": "11:37 AM - 12:13 PM", "location": "MVHS Counseling & Career Center", "details": "TBD", "title": "Club Meeting" },
  { "id": "cm-034", "host": "TBD", "monthYear": "Apr '27", "day": 27, "time": "11:37 AM - 12:13 PM", "location": "MVHS Counseling & Career Center", "details": "TBD", "title": "Club Meeting" },

  { "id": "cm-035", "host": "TBD", "monthYear": "May '27", "day": 4, "time": "11:37 AM - 12:13 PM", "location": "MVHS Counseling & Career Center", "details": "TBD", "title": "Club Meeting" },
  { "id": "cm-036", "host": "TBD", "monthYear": "May '27", "day": 11, "time": "11:37 AM - 12:13 PM", "location": "MVHS Counseling & Career Center", "details": "TBD", "title": "Club Meeting" },
  { "id": "cm-037", "host": "TBD", "monthYear": "May '27", "day": 18, "time": "11:37 AM - 12:13 PM", "location": "MVHS Counseling & Career Center", "details": "TBD", "title": "Club Meeting" },
  { "id": "cm-038", "host": "TBD", "monthYear": "May '27", "day": 25, "time": "11:37 AM - 12:13 PM", "location": "MVHS Counseling & Career Center", "details": "TBD", "title": "Club Meeting" },

  { "id": "cm-039", "host": "TBD", "monthYear": "Jun '27", "day": 1, "time": "11:37 AM - 12:13 PM", "location": "MVHS Counseling & Career Center", "details": "TBD", "title": "Club Meeting" }
]